iotile_support_firm_env_1/__init__.py
iotile_support_firm_env_1/dev_envbsl_1.py
iotile_support_firm_env_1/env_proxy.py
iotile_support_firm_env_1/envbsl_1.py
iotile_support_firm_env_1-1.2.2.dist-info/METADATA
iotile_support_firm_env_1-1.2.2.dist-info/WHEEL
iotile_support_firm_env_1-1.2.2.dist-info/entry_points.txt
iotile_support_firm_env_1-1.2.2.dist-info/top_level.txt
iotile_support_firm_env_1-1.2.2.dist-info/RECORD
