Metadata-Version: 2.1
Name: iotile-support-firm-env-1
Version: 1.2.2
Summary: UNKNOWN
Home-page: UNKNOWN
Author: Arch
Author-email: info@arch-iot.com
License: UNKNOWN
Platform: UNKNOWN
Requires-Dist: iotile-core (~=5.0)
